brigit/__init__.py
brigit/__pycache__/__init__.cpython-35.pyc
brigit/test/__init__.py
brigit/test/test_brigit.py
brigit.egg-info/PKG-INFO
brigit.egg-info/SOURCES.txt
brigit.egg-info/dependency_links.txt
brigit.egg-info/requires.txt
brigit.egg-info/top_level.txt
brigit-1.3.0.dist-info/LICENSE
brigit-1.3.0.dist-info/METADATA
brigit-1.3.0.dist-info/WHEEL
brigit-1.3.0.dist-info/top_level.txt
brigit-1.3.0.dist-info/RECORD
