Metadata-Version: 2.1
Name: brigit
Version: 1.3.0
Summary: Very simple git wrapper module
Home-page: UNKNOWN
Author: Florian Mounier - Kozea
Author-email: florian.mounier@kozea.fr
License: BSD
Platform: Any
Classifier: Development Status :: 5 - Production/Stable
Classifier: Intended Audience :: Developers
Classifier: License :: OSI Approved :: BSD License
Classifier: Operating System :: OS Independent
Classifier: Programming Language :: Python :: 2
Classifier: Programming Language :: Python :: 3
Classifier: Topic :: Software Development :: Libraries :: Python Modules
Provides: brigit
Requires-Dist: log-colorizer
